{
  "id" : "AAk1dHsznmI8mTG7zlO0wls",
  "timestamp" : "2025-11-06T09:32:01.880Z[UTC]",
  "appAppleId" : 6754452911,
  "cfBundleShortVersion" : "1.0.2",
  "cfBundleVersion" : "2",
  "deviceModel" : "iPad14,8",
  "osVersion" : "18.6.2",
  "locale" : "en-GB",
  "carrier" : null,
  "timezone" : "Europe/London",
  "architecture" : "arm64e",
  "connectionStatus" : "WI_FI",
  "pairedAppleWatch" : "",
  "appUptimeMillis" : null,
  "availableDiskBytes" : 6728556544,
  "totalDiskBytes" : 127589031936,
  "networkType" : null,
  "batteryPercentage" : 65,
  "screenWidth" : 820,
  "screenHeight" : 1180,
  "emailAddress" : "kieransaunders@mac.com",
  "comment" : "Cunt"
}